{
    "name": "trial_10",
    "start_time": "2024-10-23 08:25:37.470",
    "duration": "21.519",
    "directory": "/home/krakerlu/github/ImageMLResearch/demo/chihuahua_vs_muffin/experiments/experiment_05/output/trial_10",
    "hyperparameters": {
        "dense_units": 256,
        "dropout_rate": 0.3988108945579785,
        "learning_rate": 0.0009609575441407858
    },
    "figures": {
        "model_summary": "/home/krakerlu/github/ImageMLResearch/demo/chihuahua_vs_muffin/experiments/experiment_05/output/trial_10/model_summary.png",
        "confusion_matrix": "/home/krakerlu/github/ImageMLResearch/demo/chihuahua_vs_muffin/experiments/experiment_05/output/trial_10/confusion_matrix.png",
        "training_history": "/home/krakerlu/github/ImageMLResearch/demo/chihuahua_vs_muffin/experiments/experiment_05/output/trial_10/training_history.png"
    },
    "evaluation_metrics": {
        "train": {
            "accuracy": 1.0,
            "precision": 1.0,
            "recall": 1.0,
            "f1": 0.9999999500000026,
            "classification_report": {
                "chihuahua": {
                    "precision": 1.0,
                    "recall": 1.0,
                    "f1-score": 1.0,
                    "support": 1759
                },
                "muffin": {
                    "precision": 1.0,
                    "recall": 1.0,
                    "f1-score": 1.0,
                    "support": 1441
                },
                "micro avg": {
                    "precision": 1.0,
                    "recall": 1.0,
                    "f1-score": 1.0,
                    "support": 3200
                },
                "macro avg": {
                    "precision": 1.0,
                    "recall": 1.0,
                    "f1-score": 1.0,
                    "support": 3200
                },
                "weighted avg": {
                    "precision": 1.0,
                    "recall": 1.0,
                    "f1-score": 1.0,
                    "support": 3200
                },
                "samples avg": {
                    "precision": 1.0,
                    "recall": 1.0,
                    "f1-score": 1.0,
                    "support": 3200
                }
            }
        },
        "val": {
            "accuracy": 0.9906250238418579,
            "precision": 0.9906250238418579,
            "recall": 0.9906250238418579,
            "f1": 0.9906249738418604,
            "classification_report": {
                "chihuahua": {
                    "precision": 0.9937694704049844,
                    "recall": 0.9876160990712074,
                    "f1-score": 0.9906832298136646,
                    "support": 323
                },
                "muffin": {
                    "precision": 0.987460815047022,
                    "recall": 0.9936908517350158,
                    "f1-score": 0.9905660377358491,
                    "support": 317
                },
                "micro avg": {
                    "precision": 0.990625,
                    "recall": 0.990625,
                    "f1-score": 0.990625,
                    "support": 640
                },
                "macro avg": {
                    "precision": 0.9906151427260033,
                    "recall": 0.9906534754031115,
                    "f1-score": 0.9906246337747568,
                    "support": 640
                },
                "weighted avg": {
                    "precision": 0.9906447145479937,
                    "recall": 0.990625,
                    "f1-score": 0.9906251831126216,
                    "support": 640
                },
                "samples avg": {
                    "precision": 0.990625,
                    "recall": 0.990625,
                    "f1-score": 0.990625,
                    "support": 640
                }
            }
        },
        "test": {
            "accuracy": 0.9876819849014282,
            "precision": 0.9876819849014282,
            "recall": 0.9876819849014282,
            "f1": 0.9876819349014307,
            "classification_report": {
                "chihuahua": {
                    "precision": 0.9894957983193278,
                    "recall": 0.9874213836477987,
                    "f1-score": 0.9884575026232949,
                    "support": 477
                },
                "muffin": {
                    "precision": 0.9856115107913669,
                    "recall": 0.9879807692307693,
                    "f1-score": 0.9867947178871549,
                    "support": 416
                },
                "micro avg": {
                    "precision": 0.9876819708846585,
                    "recall": 0.9876819708846585,
                    "f1-score": 0.9876819708846585,
                    "support": 893
                },
                "macro avg": {
                    "precision": 0.9875536545553474,
                    "recall": 0.987701076439284,
                    "f1-score": 0.9876261102552248,
                    "support": 893
                },
                "weighted avg": {
                    "precision": 0.9876863205907368,
                    "recall": 0.9876819708846585,
                    "f1-score": 0.9876829018951491,
                    "support": 893
                },
                "samples avg": {
                    "precision": 0.9876819708846585,
                    "recall": 0.9876819708846585,
                    "f1-score": 0.9876819708846585,
                    "support": 893
                }
            }
        }
    },
    "training_history": {
        "accuracy": [
            0.9478124976158142,
            0.9915624856948853,
            0.9937499761581421,
            0.9934375286102295,
            0.996874988079071,
            0.9937499761581421,
            0.9959375262260437,
            0.9978125095367432,
            0.9984375238418579,
            1.0,
            1.0,
            1.0,
            1.0,
            1.0,
            1.0,
            1.0,
            1.0,
            1.0,
            1.0,
            1.0,
            1.0,
            1.0,
            1.0,
            1.0,
            1.0
        ],
        "loss": [
            0.13681931793689728,
            0.022611787542700768,
            0.018163831904530525,
            0.01792830042541027,
            0.011567606590688229,
            0.01453282218426466,
            0.00890920776873827,
            0.007840738631784916,
            0.0029682505410164595,
            0.0008975571254268289,
            0.0005361558869481087,
            0.0005116814281791449,
            0.0002776170731522143,
            0.0002630781091284007,
            0.0002682266349438578,
            0.00032870008726604283,
            0.0002683915081433952,
            0.0002024864370469004,
            0.00017657621356192976,
            0.00016032140410970896,
            0.00015897401317488402,
            0.00021658101468347013,
            0.00016310419596266001,
            0.00014523630670737475,
            0.00018061404989566654
        ],
        "val_accuracy": [
            0.9859374761581421,
            0.9859374761581421,
            0.989062488079071,
            0.9906250238418579,
            0.9859374761581421,
            0.981249988079071,
            0.981249988079071,
            0.989062488079071,
            0.9906250238418579,
            0.9906250238418579,
            0.9906250238418579,
            0.9906250238418579,
            0.9906250238418579,
            0.9906250238418579,
            0.9906250238418579,
            0.9906250238418579,
            0.9906250238418579,
            0.9906250238418579,
            0.9906250238418579,
            0.9906250238418579,
            0.9906250238418579,
            0.9906250238418579,
            0.9906250238418579,
            0.9906250238418579,
            0.9906250238418579
        ],
        "val_loss": [
            0.043935377150774,
            0.053713470697402954,
            0.05259741097688675,
            0.0499957874417305,
            0.05888334661722183,
            0.07253165543079376,
            0.06987382471561432,
            0.05085613206028938,
            0.05234263092279434,
            0.05221322923898697,
            0.05416247993707657,
            0.055832065641880035,
            0.05679236724972725,
            0.057962287217378616,
            0.05911223962903023,
            0.06009889394044876,
            0.06069286912679672,
            0.061704494059085846,
            0.062357474118471146,
            0.06297829002141953,
            0.06362422555685043,
            0.06449009478092194,
            0.06513980776071548,
            0.06491361558437347,
            0.06576220691204071
        ]
    }
}